odoo/addons/event_registration_multi_qty/README.rst
odoo/addons/event_registration_multi_qty/__init__.py
odoo/addons/event_registration_multi_qty/__manifest__.py
odoo/addons/event_registration_multi_qty/i18n/es.po
odoo/addons/event_registration_multi_qty/i18n/event_registration_multi_qty.pot
odoo/addons/event_registration_multi_qty/i18n/it.po
odoo/addons/event_registration_multi_qty/models/__init__.py
odoo/addons/event_registration_multi_qty/models/event.py
odoo/addons/event_registration_multi_qty/readme/CONFIGURE.md
odoo/addons/event_registration_multi_qty/readme/CONTRIBUTORS.md
odoo/addons/event_registration_multi_qty/readme/DESCRIPTION.md
odoo/addons/event_registration_multi_qty/readme/USAGE.md
odoo/addons/event_registration_multi_qty/static/description/icon.png
odoo/addons/event_registration_multi_qty/static/description/index.html
odoo/addons/event_registration_multi_qty/tests/__init__.py
odoo/addons/event_registration_multi_qty/tests/test_event_registration_multi_qty.py
odoo/addons/event_registration_multi_qty/views/event_view.xml
odoo_addon_event_registration_multi_qty-18.0.1.0.0.2.dist-info/METADATA
odoo_addon_event_registration_multi_qty-18.0.1.0.0.2.dist-info/WHEEL
odoo_addon_event_registration_multi_qty-18.0.1.0.0.2.dist-info/top_level.txt
odoo_addon_event_registration_multi_qty-18.0.1.0.0.2.dist-info/RECORD
